liuyuanlin/__init__.py
liuyuanlin/__main__.py
liuyuanlin-2.0.1.dist-info/LICENSE
liuyuanlin-2.0.1.dist-info/METADATA
liuyuanlin-2.0.1.dist-info/WHEEL
liuyuanlin-2.0.1.dist-info/entry_points.txt
liuyuanlin-2.0.1.dist-info/top_level.txt
liuyuanlin-2.0.1.dist-info/RECORD
