Metadata-Version: 2.1
Name: liuyuanlin
Version: 2.0.1
Summary: This is a gift for liumenghan.
Home-page: https://github.com/MisakaMikoto128/liuyuanlin
Author: liuyuanlin
Author-email: liuyuanlins@outlook.com
Project-URL: Bug Tracker, https://github.com/MisakaMikoto128/liuyuanlin/issues
Classifier: Programming Language :: Python :: 3
Classifier: License :: OSI Approved :: MIT License
Classifier: Operating System :: OS Independent
Requires-Python: >=3.6
License-File: LICENSE
Requires-Dist: numpy (>=1.20.1)
Requires-Dist: opencv-python (>=4.5.1.48)
